pytest_toolbox/__init__.py
pytest_toolbox/comparison.py
pytest_toolbox/main.py
pytest_toolbox/version.py
pytest_toolbox-0.4.dist-info/METADATA
pytest_toolbox-0.4.dist-info/RECORD
pytest_toolbox-0.4.dist-info/WHEEL
pytest_toolbox-0.4.dist-info/entry_points.txt
pytest_toolbox-0.4.dist-info/top_level.txt
pytest_toolbox-0.4.dist-info/zip-safe
