Metadata-Version: 2.1
Name: pytest-toolbox
Version: 0.4
Summary: Numerous useful plugins for pytest.
Home-page: https://github.com/samuelcolvin/pytest-toolbox
Author: Samuel Colvin
Author-email: S@muelColvin.com
License: MIT
Keywords: pytest,plugin,toolbox
Platform: any
Classifier: Environment :: Console
Classifier: Intended Audience :: Developers
Classifier: License :: OSI Approved :: MIT License
Classifier: Programming Language :: Python
Classifier: Programming Language :: Python :: 3
Classifier: Programming Language :: Python :: 3.4
Classifier: Programming Language :: Python :: 3.5
Classifier: Topic :: Software Development :: Testing
Classifier: Framework :: Pytest
Requires-Python: >=3.5
Requires-Dist: pytest (>=3.5.0)
